ler_arquivos/__init__.py
ler_arquivos/ler_arquivos.py
ler_arquivos-0.0.1.dist-info/METADATA
ler_arquivos-0.0.1.dist-info/WHEEL
ler_arquivos-0.0.1.dist-info/top_level.txt
ler_arquivos-0.0.1.dist-info/RECORD
