Metadata-Version: 2.1
Name: ler-arquivos
Version: 0.0.1
Summary: Pacote para ler arquivos Excel a partir de URLs
Home-page: https://github.com/CientistaPY/desafios_dio/tree/main/Forma%C3%A7%C3%A3o%20Python%20Developer/TratamentodeDadoscomPython2
Author: Luis Pontes
Author-email: mailtoluiscarlos@gmail.com
Requires-Python: >=3.8
Requires-Dist: pandas
